flask_redis_ex/__init__.py
flask_redis_ex-0.0.4.dist-info/LICENSE
flask_redis_ex-0.0.4.dist-info/METADATA
flask_redis_ex-0.0.4.dist-info/WHEEL
flask_redis_ex-0.0.4.dist-info/top_level.txt
flask_redis_ex-0.0.4.dist-info/RECORD
