Metadata-Version: 2.1
Name: flask-redis-ex
Version: 0.0.4
Summary: Simple to use redis in flask.
Home-page: https://gitee.com/krealseu/flask-redis-ex
Author: krealseu
Author-email: lthee12@hotmail.com
License: MIT
Keywords: flask,redis
License-File: LICENSE
Requires-Dist: Flask (>=0.8)
Requires-Dist: redis (>=2.7.6)
